wgutil/__init__.py
wgutil/cli.py
wgutil/iface.py
wgutil/peer.py
wgutil/wg.py
wgutil-0.0.3.dist-info/licenses/LICENSE
wgutil-0.0.3.dist-info/METADATA
wgutil-0.0.3.dist-info/WHEEL
wgutil-0.0.3.dist-info/entry_points.txt
wgutil-0.0.3.dist-info/top_level.txt
wgutil-0.0.3.dist-info/RECORD
