Metadata-Version: 2.4
Name: wgutil
Version: 0.0.3
Summary: wireguard util
Author-email: qq1u <609799548@qq.com>
License-Expression: MIT
Project-URL: Homepage, https://github.com/qq1u/wgutil
Project-URL: Issues, https://github.com/qq1u/wgutil/issues
Classifier: Programming Language :: Python :: 3
Classifier: Operating System :: OS Independent
Requires-Python: >=3
License-File: LICENSE
Requires-Dist: psutil
Requires-Dist: qrcode
Dynamic: license-file
